<?xml version="1.0" encoding="utf-8"?>
<StructureDefinition xmlns="http://hl7.org/fhir">
  <id value="au-core-medicationdispense"/>
  <extension url="http://hl7.org/fhir/StructureDefinition/structuredefinition-fmm">
    <valueInteger value="0"/>
  </extension>
  <url value="http://hl7.org.au/fhir/core/StructureDefinition/au-core-medicationdispense"/>
  <name value="AUCoreMedicationDispense"/>
  <title value="AU Core MedicationDispense"/>
  <status value="draft"/>
  <description value="This profile sets minimum expectations for a MedicationDispense resource to record, search, and fetch the supply of a medication (i.e. dispense) associated with a patient. It is based on the [AU Base MedicationDispense](http://build.fhir.org/ig/hl7au/au-fhir-base/StructureDefinition-au-medicationdispense.html) profile and identifies the *additional* mandatory core elements, extensions, vocabularies and value sets that **SHALL** be present in the MedicationDispense when conforming to this profile. It provides the floor for standards development for specific uses cases in an Australian context." />
  <kind value="resource"/>
  <abstract value="false"/>
  <type value="MedicationDispense"/>
  <baseDefinition value="http://hl7.org.au/fhir/StructureDefinition/au-medicationdispense"/>
  <derivation value="constraint"/>
  <differential>
    <element id="MedicationDispense">
      <path value="MedicationDispense"/>
    </element>
    <element id="MedicationDispense.status">
      <extension url="http://hl7.org/fhir/StructureDefinition/obligation">
        <extension url="code">
          <valueCode value="SHALL:populate-if-known"/>
        </extension>
        <extension url="actor">
          <valueCanonical value="http://hl7.org.au/fhir/core/ActorDefinition/au-core-actor-responder"/>
        </extension>
      </extension>
      <extension url="http://hl7.org/fhir/StructureDefinition/obligation">
        <extension url="code">
          <valueCode value="SHALL:no-error"/>
        </extension>
        <extension url="actor">
          <valueCanonical value="http://hl7.org.au/fhir/core/ActorDefinition/au-core-actor-requester"/>
        </extension>
      </extension>
      <path value="MedicationDispense.status"/>
      <mustSupport value="true"/>
    </element>
    <element id="MedicationDispense.medication[x]">
      <extension url="http://hl7.org/fhir/StructureDefinition/obligation">
        <extension url="code">
          <valueCode value="SHALL:populate-if-known"/>
        </extension>
        <extension url="actor">
          <valueCanonical value="http://hl7.org.au/fhir/core/ActorDefinition/au-core-actor-responder"/>
        </extension>
      </extension>
      <extension url="http://hl7.org/fhir/StructureDefinition/obligation">
        <extension url="code">
          <valueCode value="SHALL:no-error"/>
        </extension>
        <extension url="actor">
          <valueCanonical value="http://hl7.org.au/fhir/core/ActorDefinition/au-core-actor-requester"/>
        </extension>
      </extension>
      <path value="MedicationDispense.medication[x]"/>
      <slicing>
        <discriminator>
          <type value="type"/>
          <path value="$this"/>
        </discriminator>
        <rules value="closed"/>
      </slicing>
      <mustSupport value="true"/>
    </element>
    <element id="MedicationDispense.medication[x]:medicationCodeableConcept">
      <extension url="http://hl7.org/fhir/StructureDefinition/obligation">
        <extension url="code">
          <valueCode value="SHALL:populate-if-known"/>
        </extension>
        <extension url="actor">
          <valueCanonical value="http://hl7.org.au/fhir/core/ActorDefinition/au-core-actor-responder"/>
        </extension>
      </extension>
      <extension url="http://hl7.org/fhir/StructureDefinition/obligation">
        <extension url="code">
          <valueCode value="SHALL:no-error"/>
        </extension>
        <extension url="actor">
          <valueCanonical value="http://hl7.org.au/fhir/core/ActorDefinition/au-core-actor-requester"/>
        </extension>
      </extension>
      <path value="MedicationDispense.medication[x]"/>
      <sliceName value="medicationCodeableConcept"/>
      <type>
        <code value="CodeableConcept"/>
      </type>
      <mustSupport value="true"/>
    </element>
    <element id="MedicationDispense.medication[x]:medicationCodeableConcept.coding">
      <path value="MedicationDispense.medication[x].coding"/>
      <slicing>
        <discriminator>
          <type value="pattern" />
          <path value="$this" />
        </discriminator>
        <rules value="open"/>
      </slicing>
    </element>
    <element id="MedicationDispense.medication[x]:medicationCodeableConcept.coding:pbs">
      <extension url="http://hl7.org/fhir/StructureDefinition/obligation">
        <extension url="code">
          <valueCode value="SHALL:populate-if-known"/>
        </extension>
        <extension url="actor">
          <valueCanonical value="http://hl7.org.au/fhir/core/ActorDefinition/au-core-actor-responder"/>
        </extension>
      </extension>
      <extension url="http://hl7.org/fhir/StructureDefinition/obligation">
        <extension url="code">
          <valueCode value="SHALL:no-error"/>
        </extension>
        <extension url="actor">
          <valueCanonical value="http://hl7.org.au/fhir/core/ActorDefinition/au-core-actor-requester"/>
        </extension>
      </extension>
      <path value="MedicationDispense.medication[x].coding"/>
      <sliceName value="pbs"/>
      <binding>
        <strength value="required" />
        <valueSet value="http://terminology.hl7.org.au/ValueSet/pbs-item" />
      </binding>
      <mustSupport value="true"/>
    </element>
    <element id="MedicationDispense.medication[x]:medicationCodeableConcept.coding:amt">
      <extension url="http://hl7.org/fhir/StructureDefinition/obligation">
        <extension url="code">
          <valueCode value="SHALL:populate-if-known"/>
        </extension>
        <extension url="actor">
          <valueCanonical value="http://hl7.org.au/fhir/core/ActorDefinition/au-core-actor-responder"/>
        </extension>
      </extension>
      <extension url="http://hl7.org/fhir/StructureDefinition/obligation">
        <extension url="code">
          <valueCode value="SHALL:no-error"/>
        </extension>
        <extension url="actor">
          <valueCanonical value="http://hl7.org.au/fhir/core/ActorDefinition/au-core-actor-requester"/>
        </extension>
      </extension>
      <path value="MedicationDispense.medication[x].coding"/>
      <sliceName value="amt"/>
      <binding>
        <strength value="required" />
        <valueSet value="https://healthterminologies.gov.au/fhir/ValueSet/australian-medication-1" />
      </binding>
      <mustSupport value="true"/>
    </element>
    <element id="MedicationDispense.medication[x]:medicationReference">
      <extension url="http://hl7.org/fhir/StructureDefinition/obligation">
        <extension url="code">
          <valueCode value="SHALL:populate-if-known"/>
        </extension>
        <extension url="actor">
          <valueCanonical value="http://hl7.org.au/fhir/core/ActorDefinition/au-core-actor-responder"/>
        </extension>
      </extension>
      <extension url="http://hl7.org/fhir/StructureDefinition/obligation">
        <extension url="code">
          <valueCode value="SHALL:no-error"/>
        </extension>
        <extension url="actor">
          <valueCanonical value="http://hl7.org.au/fhir/core/ActorDefinition/au-core-actor-requester"/>
        </extension>
      </extension>
      <path value="MedicationDispense.medication[x]"/>
      <sliceName value="medicationReference"/>
      <type>
        <code value="Reference"/>
        <targetProfile value="http://hl7.org.au/fhir/core/StructureDefinition/au-core-medication"/>
      </type>
      <mustSupport value="true"/>
    </element>
    <element id="MedicationDispense.subject">
      <extension url="http://hl7.org/fhir/StructureDefinition/obligation">
        <extension url="code">
          <valueCode value="SHALL:populate-if-known"/>
        </extension>
        <extension url="actor">
          <valueCanonical value="http://hl7.org.au/fhir/core/ActorDefinition/au-core-actor-responder"/>
        </extension>
      </extension>
      <extension url="http://hl7.org/fhir/StructureDefinition/obligation">
        <extension url="code">
          <valueCode value="SHALL:no-error"/>
        </extension>
        <extension url="actor">
          <valueCanonical value="http://hl7.org.au/fhir/core/ActorDefinition/au-core-actor-requester"/>
        </extension>
      </extension>
      <path value="MedicationDispense.subject"/>
      <min value="1"/>
      <type>
        <code value="Reference"/>
        <targetProfile value="http://hl7.org.au/fhir/core/StructureDefinition/au-core-patient"/>
      </type>
      <mustSupport value="true"/>
    </element>
    <element id="MedicationDispense.context">
      <extension url="http://hl7.org/fhir/StructureDefinition/obligation">
        <extension url="code">
          <valueCode value="SHALL:populate-if-known"/>
        </extension>
        <extension url="actor">
          <valueCanonical value="http://hl7.org.au/fhir/core/ActorDefinition/au-core-actor-responder"/>
        </extension>
      </extension>
      <extension url="http://hl7.org/fhir/StructureDefinition/obligation">
        <extension url="code">
          <valueCode value="SHALL:no-error"/>
        </extension>
        <extension url="actor">
          <valueCanonical value="http://hl7.org.au/fhir/core/ActorDefinition/au-core-actor-requester"/>
        </extension>
      </extension>
      <path value="MedicationDispense.context"/>
      <type>
        <code value="Reference"/>
        <targetProfile value="http://hl7.org.au/fhir/core/StructureDefinition/au-core-encounter"/>
      </type>
      <mustSupport value="true"/>
    </element>
    <element id="MedicationDispense.performer">
      <extension url="http://hl7.org/fhir/StructureDefinition/obligation">
        <extension url="code">
          <valueCode value="SHALL:populate-if-known"/>
        </extension>
        <extension url="actor">
          <valueCanonical value="http://hl7.org.au/fhir/core/ActorDefinition/au-core-actor-responder"/>
        </extension>
      </extension>
      <extension url="http://hl7.org/fhir/StructureDefinition/obligation">
        <extension url="code">
          <valueCode value="SHALL:no-error"/>
        </extension>
        <extension url="actor">
          <valueCanonical value="http://hl7.org.au/fhir/core/ActorDefinition/au-core-actor-requester"/>
        </extension>
      </extension>
      <path value="MedicationDispense.performer"/>
      <mustSupport value="true"/>
    </element>
    <element id="MedicationDispense.performer.actor">
      <extension url="http://hl7.org/fhir/StructureDefinition/obligation">
        <extension url="code">
          <valueCode value="SHALL:populate-if-known"/>
        </extension>
        <extension url="actor">
          <valueCanonical value="http://hl7.org.au/fhir/core/ActorDefinition/au-core-actor-responder"/>
        </extension>
      </extension>
      <extension url="http://hl7.org/fhir/StructureDefinition/obligation">
        <extension url="code">
          <valueCode value="SHALL:no-error"/>
        </extension>
        <extension url="actor">
          <valueCanonical value="http://hl7.org.au/fhir/core/ActorDefinition/au-core-actor-requester"/>
        </extension>
      </extension>
      <path value="MedicationDispense.performer.actor"/>
      <type>
        <code value="Reference"/>
        <targetProfile value="http://hl7.org.au/fhir/core/StructureDefinition/au-core-practitioner" />
        <targetProfile value="http://hl7.org.au/fhir/core/StructureDefinition/au-core-practitionerrole"/>
        <targetProfile value="http://hl7.org.au/fhir/core/StructureDefinition/au-core-organization"/>
        <targetProfile value="http://hl7.org.au/fhir/core/StructureDefinition/au-core-patient"/>
        <targetProfile value="http://hl7.org.au/fhir/core/StructureDefinition/au-core-relatedperson"/>
      </type>
      <mustSupport value="true"/>
    </element>
    <element id="MedicationDispense.authorizingPrescription">
      <extension url="http://hl7.org/fhir/StructureDefinition/obligation">
        <extension url="code">
          <valueCode value="SHALL:populate-if-known"/>
        </extension>
        <extension url="actor">
          <valueCanonical value="http://hl7.org.au/fhir/core/ActorDefinition/au-core-actor-responder"/>
        </extension>
      </extension>
      <extension url="http://hl7.org/fhir/StructureDefinition/obligation">
        <extension url="code">
          <valueCode value="SHALL:no-error"/>
        </extension>
        <extension url="actor">
          <valueCanonical value="http://hl7.org.au/fhir/core/ActorDefinition/au-core-actor-requester"/>
        </extension>
      </extension>
      <path value="MedicationDispense.authorizingPrescription"/>
      <type>
        <code value="Reference"/>
        <targetProfile value="http://hl7.org.au/fhir/core/StructureDefinition/au-core-medicationrequest"/>
      </type>
      <mustSupport value="true"/>
    </element>
    <element id="MedicationDispense.type">
      <extension url="http://hl7.org/fhir/StructureDefinition/obligation">
        <extension url="code">
          <valueCode value="SHALL:populate-if-known"/>
        </extension>
        <extension url="actor">
          <valueCanonical value="http://hl7.org.au/fhir/core/ActorDefinition/au-core-actor-responder"/>
        </extension>
      </extension>
      <extension url="http://hl7.org/fhir/StructureDefinition/obligation">
        <extension url="code">
          <valueCode value="SHALL:no-error"/>
        </extension>
        <extension url="actor">
          <valueCanonical value="http://hl7.org.au/fhir/core/ActorDefinition/au-core-actor-requester"/>
        </extension>
      </extension>
      <path value="MedicationDispense.type"/>
      <mustSupport value="true"/>
    </element>
    <element id="MedicationDispense.quantity">
      <extension url="http://hl7.org/fhir/StructureDefinition/obligation">
        <extension url="code">
          <valueCode value="SHALL:populate-if-known"/>
        </extension>
        <extension url="actor">
          <valueCanonical value="http://hl7.org.au/fhir/core/ActorDefinition/au-core-actor-responder"/>
        </extension>
      </extension>
      <extension url="http://hl7.org/fhir/StructureDefinition/obligation">
        <extension url="code">
          <valueCode value="SHALL:no-error"/>
        </extension>
        <extension url="actor">
          <valueCanonical value="http://hl7.org.au/fhir/core/ActorDefinition/au-core-actor-requester"/>
        </extension>
      </extension>
      <path value="MedicationDispense.quantity"/>
      <mustSupport value="true"/>
    </element>
    <element id="MedicationDispense.whenPrepared">
      <extension url="http://hl7.org/fhir/StructureDefinition/obligation">
        <extension url="code">
          <valueCode value="SHALL:populate-if-known"/>
        </extension>
        <extension url="actor">
          <valueCanonical value="http://hl7.org.au/fhir/core/ActorDefinition/au-core-actor-responder"/>
        </extension>
      </extension>
      <extension url="http://hl7.org/fhir/StructureDefinition/obligation">
        <extension url="code">
          <valueCode value="SHALL:no-error"/>
        </extension>
        <extension url="actor">
          <valueCanonical value="http://hl7.org.au/fhir/core/ActorDefinition/au-core-actor-requester"/>
        </extension>
      </extension>
      <path value="MedicationDispense.whenPrepared"/>
      <condition value="au-core-meddisp-02"/>
      <constraint>
        <key value="au-core-meddisp-02"/>
        <severity value="error"/>
        <human value="Date shall be precise to the day or, if not available, the Data Absent Reason extension shall be present"/>
        <expression value="$this.hasValue() implies (extension('http://hl7.org/fhir/StructureDefinition/data-absent-reason').value.exists().not() and $this.toString().length() >= 10)"/>
        <xpath value="(f:whenPrepared[string-length(.)>=10]) and not(exists(f:extension[@url='http://hl7.org/fhir/StructureDefinition/data-absent-reason'])))"/>
        <source value="http://hl7.org.au/fhir/core/StructureDefinition/au-core-medicationdispense"/>
      </constraint>
      <mustSupport value="true"/>
    </element>
    <element id="MedicationDispense.whenHandedOver">
      <extension url="http://hl7.org/fhir/StructureDefinition/obligation">
        <extension url="code">
          <valueCode value="SHALL:populate-if-known"/>
        </extension>
        <extension url="actor">
          <valueCanonical value="http://hl7.org.au/fhir/core/ActorDefinition/au-core-actor-responder"/>
        </extension>
      </extension>
      <extension url="http://hl7.org/fhir/StructureDefinition/obligation">
        <extension url="code">
          <valueCode value="SHALL:no-error"/>
        </extension>
        <extension url="actor">
          <valueCanonical value="http://hl7.org.au/fhir/core/ActorDefinition/au-core-actor-requester"/>
        </extension>
      </extension>
      <path value="MedicationDispense.whenHandedOver"/>
      <condition value="au-core-meddisp-01"/>
      <constraint>
        <key value="au-core-meddisp-01"/>
        <severity value="error"/>
        <human value="Date shall be precise to the day or, if not available, the Data Absent Reason extension shall be present"/>
        <expression value="$this.hasValue() implies (extension('http://hl7.org/fhir/StructureDefinition/data-absent-reason').value.exists().not() and $this.toString().length() >= 10)"/>
        <xpath value="(f:whenHandedOver[string-length(.)>=10]) and not(exists(f:extension[@url='http://hl7.org/fhir/StructureDefinition/data-absent-reason'])))"/>
        <source value="http://hl7.org.au/fhir/core/StructureDefinition/au-core-medicationdispense"/>
      </constraint>
      <mustSupport value="true"/>
    </element>
    <element id="MedicationDispense.dosageInstruction">
      <extension url="http://hl7.org/fhir/StructureDefinition/obligation">
        <extension url="code">
          <valueCode value="SHALL:populate-if-known"/>
        </extension>
        <extension url="actor">
          <valueCanonical value="http://hl7.org.au/fhir/core/ActorDefinition/au-core-actor-responder"/>
        </extension>
      </extension>
      <extension url="http://hl7.org/fhir/StructureDefinition/obligation">
        <extension url="code">
          <valueCode value="SHALL:no-error"/>
        </extension>
        <extension url="actor">
          <valueCanonical value="http://hl7.org.au/fhir/core/ActorDefinition/au-core-actor-requester"/>
        </extension>
      </extension>
      <path value="MedicationDispense.dosageInstruction"/>
      <mustSupport value="true"/>
    </element>
    <element id="MedicationDispense.dosageInstruction.text">
      <extension url="http://hl7.org/fhir/StructureDefinition/obligation">
        <extension url="code">
          <valueCode value="SHALL:populate-if-known"/>
        </extension>
        <extension url="actor">
          <valueCanonical value="http://hl7.org.au/fhir/core/ActorDefinition/au-core-actor-responder"/>
        </extension>
      </extension>
      <extension url="http://hl7.org/fhir/StructureDefinition/obligation">
        <extension url="code">
          <valueCode value="SHALL:no-error"/>
        </extension>
        <extension url="actor">
          <valueCanonical value="http://hl7.org.au/fhir/core/ActorDefinition/au-core-actor-requester"/>
        </extension>
      </extension>
      <path value="MedicationDispense.dosageInstruction.text" />
      <mustSupport value="true" />
    </element>
  </differential>
</StructureDefinition>
